{
    "DocType": "dDocument_Service",
    "CardCode": "CCHD0012",
    "DocDate": "2025-06-16",
    "Comments": "Exportación Detalle Liquidación ID 5",
    "U_NIT": "321052",
    "Series": 82,
    "DocTotal": "777.00",
    "Reference1": "5",
    "NumAtCard": "DLIQ-5-20250609T100600",
    "DocCurrency": "QTZ",
    "DocRate": 1,
    "DocumentLines": [
        {
            "LineType": 0,
            "ItemDescription": "Hospedaje",
            "Price": 21.93,
            "TaxCode": "IVA",
            "CostingCode": "D08",
            "AccountCode": "641101001"
        },
        {
            "LineType": 1,
            "ItemDescription": "INGUAT",
            "Price": 18.28,
            "TaxCode": "EXE",
            "CostingCode": "D08",
            "AccountCode": "641101001"
        },
        {
            "LineType": 2,
            "ItemDescription": "Hospedaje",
            "Price": 31.67,
            "TaxCode": "IVA",
            "CostingCode": "D08",
            "AccountCode": "641101001"
        },
        {
            "LineType": 3,
            "ItemDescription": "INGUAT",
            "Price": 26.39,
            "TaxCode": "EXE",
            "CostingCode": "D08",
            "AccountCode": "641101001"
        }
    ]
}